setup.cfg
setup.py
kimonolabs/__init__.py
pykimonolabs.egg-info/PKG-INFO
pykimonolabs.egg-info/SOURCES.txt
pykimonolabs.egg-info/dependency_links.txt
pykimonolabs.egg-info/not-zip-safe
pykimonolabs.egg-info/pbr.json
pykimonolabs.egg-info/top_level.txt