Metadata-Version: 1.0
Name: pykimonolabs
Version: 0.1.4
Summary: Python library to access APIs created on kimonolabs.com
Home-page: http://github.com/cyriac/pykimonolabs
Author: Cyriac Thomas
Author-email: me@cyriacthomas.com
License: MIT
Platform: UNKNOWN
